Changelog
MANIFEST.in
README
setup.py
bin/ggz
bin/ggz-fleet
bin/ggz-irc
bin/ggz-sleek
bin/ggz-tornado
ggz/__init__.py
ggz/imports.py
ggz/memcached.py
ggz/version.py
ggz/contrib/__init__.py
ggz/contrib/feedparser.py
ggz/contrib/memcache.py
ggz/contrib/rijndael.py
ggz/contrib/sgmllib.py
ggz/contrib/sgmllib3.py
ggz/contrib/bs4/__init__.py
ggz/contrib/bs4/dammit.py
ggz/contrib/bs4/element.py
ggz/contrib/bs4/testing.py
ggz/contrib/bs4/builder/__init__.py
ggz/contrib/bs4/builder/_html5lib.py
ggz/contrib/bs4/builder/_htmlparser.py
ggz/contrib/bs4/builder/_lxml.py
ggz/contrib/sleekxmpp/__init__.py
ggz/contrib/sleekxmpp/basexmpp.py
ggz/contrib/sleekxmpp/clientxmpp.py
ggz/contrib/sleekxmpp/componentxmpp.py
ggz/contrib/sleekxmpp/exceptions.py
ggz/contrib/sleekxmpp/version.py
ggz/contrib/sleekxmpp/features/__init__.py
ggz/contrib/sleekxmpp/features/feature_bind/__init__.py
ggz/contrib/sleekxmpp/features/feature_bind/bind.py
ggz/contrib/sleekxmpp/features/feature_bind/stanza.py
ggz/contrib/sleekxmpp/features/feature_mechanisms/__init__.py
ggz/contrib/sleekxmpp/features/feature_mechanisms/mechanisms.py
ggz/contrib/sleekxmpp/features/feature_mechanisms/stanza/__init__.py
ggz/contrib/sleekxmpp/features/feature_mechanisms/stanza/auth.py
ggz/contrib/sleekxmpp/features/feature_mechanisms/stanza/challenge.py
ggz/contrib/sleekxmpp/features/feature_mechanisms/stanza/failure.py
ggz/contrib/sleekxmpp/features/feature_mechanisms/stanza/mechanisms.py
ggz/contrib/sleekxmpp/features/feature_mechanisms/stanza/response.py
ggz/contrib/sleekxmpp/features/feature_mechanisms/stanza/success.py
ggz/contrib/sleekxmpp/features/feature_session/__init__.py
ggz/contrib/sleekxmpp/features/feature_session/session.py
ggz/contrib/sleekxmpp/features/feature_session/stanza.py
ggz/contrib/sleekxmpp/features/feature_starttls/__init__.py
ggz/contrib/sleekxmpp/features/feature_starttls/stanza.py
ggz/contrib/sleekxmpp/features/feature_starttls/starttls.py
ggz/contrib/sleekxmpp/plugins/__init__.py
ggzbot.egg-info/PKG-INFO
ggzbot.egg-info/SOURCES.txt
ggzbot.egg-info/dependency_links.txt
ggzbot.egg-info/not-zip-safe
ggzbot.egg-info/top_level.txt