Metadata-Version: 1.1
Name: ggzbot
Version: 0.1.2
Summary: supporting the GGZ patients since 14-9-2012
Home-page: http://ggzbot.googlecode.com/
Author: Bart Thate
Author-email: ggzpreventie@gmail.com
License: MIT
Download-URL: http://code.google.com/p/ggzbot/downloads
Platform: UNKNOWN
Classifier: Development Status :: 3 - Alpha
Classifier: Environment :: Console
Classifier: Environment :: Other Environment
Classifier: Intended Audience :: Developers
Classifier: License :: OSI Approved :: MIT License
Classifier: Operating System :: Unix
Classifier: Programming Language :: Python
Classifier: Topic :: Communications :: Chat
Classifier: Topic :: Software Development :: Libraries :: Python Modules
